{"officierGarde": ["609bc56eaf3b360120dadd43", "609bc580af3b360120dadd45", "609bc59faf3b360120dadd48", "609bc5b4af3b360120dadd4b"], "radioService": ["609bc595af3b360120dadd47"], "maitreService": ["609bc5acaf3b360120dadd4a"], "quartCoupee": [], "quartMachine": [], "capitaineArme": ["609bc5a5af3b360120dadd49"], "infirmier": ["609bc32291aed9d6ba4d10c1"], "sc": ["609bc58caf3b360120dadd46"], "comie": [], "boulongier": [], "cuisinier": [], "maitreHotel": ["609bc56eaf3b360120dadd42"], "stage": [], "consultation": [], "absent": [], "ptc": [], "ronde": []}